rpa_common/Common.py
rpa_common/Env.py
rpa_common/Mitmdump.py
rpa_common/__init__.py
rpa_common/config/__init__.py
rpa_common/config/development/__init__.py
rpa_common/config/development/rabbitmq.py
rpa_common/config/development/server.py
rpa_common/config/production/__init__.py
rpa_common/config/production/rabbitmq.py
rpa_common/config/production/server.py
rpa_common/config/test/__init__.py
rpa_common/config/test/rabbitmq.py
rpa_common/config/test/server.py
rpa_common/drive/__init__.py
rpa_common/drive/chrome/__init__.py
rpa_common/drive/chrome/chromedriver/__init__.py
rpa_common/drive/chrome/chromedriver/linux/__init__.py
rpa_common/drive/chrome/chromedriver/linux/138/__init__.py
rpa_common/drive/chrome/chromedriver/windows/__init__.py
rpa_common/exceptions/Api.py
rpa_common/exceptions/Base.py
rpa_common/exceptions/Env.py
rpa_common/exceptions/Login.py
rpa_common/exceptions/Params.py
rpa_common/exceptions/Task.py
rpa_common/exceptions/Unknown.py
rpa_common/exceptions/__init__.py
rpa_common/library/AdsPower.py
rpa_common/library/Chrome.py
rpa_common/library/Crontab.py
rpa_common/library/Decorator.py
rpa_common/library/Env.py
rpa_common/library/Logger.py
rpa_common/library/Queue.py
rpa_common/library/Request.py
rpa_common/library/Run.py
rpa_common/library/Task.py
rpa_common/library/__init__.py
rpa_common/request/ShopRequest.py
rpa_common/request/TaskRequest.py
rpa_common/request/__init__.py
rpa_common/service/EmailService.py
rpa_common/service/ExecuteService.py
rpa_common/service/GoogleService.py
rpa_common/service/__init__.py
rpa_common-1.0.28.dist-info/LICENSE
rpa_common-1.0.28.dist-info/METADATA
rpa_common-1.0.28.dist-info/WHEEL
rpa_common-1.0.28.dist-info/top_level.txt
rpa_common-1.0.28.dist-info/RECORD
